whoosh/__init__.py
whoosh/classify.py
whoosh/collectors.py
whoosh/columns.py
whoosh/compat.py
whoosh/externalsort.py
whoosh/fields.py
whoosh/formats.py
whoosh/highlight.py
whoosh/idsets.py
whoosh/index.py
whoosh/legacy.py
whoosh/multiproc.py
whoosh/reading.py
whoosh/scoring.py
whoosh/searching.py
whoosh/sorting.py
whoosh/spelling.py
whoosh/system.py
whoosh/writing.py
whoosh/analysis/__init__.py
whoosh/analysis/acore.py
whoosh/analysis/analyzers.py
whoosh/analysis/filters.py
whoosh/analysis/intraword.py
whoosh/analysis/morph.py
whoosh/analysis/ngrams.py
whoosh/analysis/tokenizers.py
whoosh/automata/__init__.py
whoosh/automata/fsa.py
whoosh/automata/fst.py
whoosh/automata/glob.py
whoosh/automata/lev.py
whoosh/automata/nfa.py
whoosh/automata/reg.py
whoosh/codec/__init__.py
whoosh/codec/base.py
whoosh/codec/memory.py
whoosh/codec/plaintext.py
whoosh/codec/whoosh2.py
whoosh/codec/whoosh3.py
whoosh/filedb/__init__.py
whoosh/filedb/compound.py
whoosh/filedb/fileindex.py
whoosh/filedb/filepostings.py
whoosh/filedb/filereading.py
whoosh/filedb/filestore.py
whoosh/filedb/filetables.py
whoosh/filedb/filewriting.py
whoosh/filedb/gae.py
whoosh/filedb/misc.py
whoosh/filedb/pools.py
whoosh/filedb/structfile.py
whoosh/lang/__init__.py
whoosh/lang/dmetaphone.py
whoosh/lang/isri.py
whoosh/lang/lovins.py
whoosh/lang/morph_en.py
whoosh/lang/paicehusk.py
whoosh/lang/phonetic.py
whoosh/lang/porter.py
whoosh/lang/porter2.py
whoosh/lang/stopwords.py
whoosh/lang/wordnet.py
whoosh/lang/snowball/__init__.py
whoosh/lang/snowball/bases.py
whoosh/lang/snowball/danish.py
whoosh/lang/snowball/dutch.py
whoosh/lang/snowball/english.py
whoosh/lang/snowball/finnish.py
whoosh/lang/snowball/french.py
whoosh/lang/snowball/german.py
whoosh/lang/snowball/hungarian.py
whoosh/lang/snowball/italian.py
whoosh/lang/snowball/norwegian.py
whoosh/lang/snowball/portugese.py
whoosh/lang/snowball/romanian.py
whoosh/lang/snowball/russian.py
whoosh/lang/snowball/spanish.py
whoosh/lang/snowball/swedish.py
Whoosh_Reloaded-2.7.5.dist-info/LICENSE.txt
Whoosh_Reloaded-2.7.5.dist-info/METADATA
Whoosh_Reloaded-2.7.5.dist-info/WHEEL
Whoosh_Reloaded-2.7.5.dist-info/top_level.txt
Whoosh_Reloaded-2.7.5.dist-info/zip-safe
Whoosh_Reloaded-2.7.5.dist-info/RECORD
