Metadata-Version: 2.1
Name: Whoosh-Reloaded
Version: 2.7.5
Summary: Fast, pure-Python full text indexing, search, and spell checking library.
Home-page: https://github.com/Sygil-Dev/whoosh-reloaded
Author: Matt Chaput
Author-email: matt@whoosh.ca
Maintainer: Sygil-Dev
License: Two-clause BSD license
Keywords: index search text spell
Classifier: Programming Language :: Python :: 3
Classifier: Development Status :: 5 - Production/Stable
Classifier: Intended Audience :: Developers
Classifier: License :: OSI Approved :: BSD License
Classifier: Natural Language :: English
Classifier: Operating System :: OS Independent
Classifier: Programming Language :: Python :: 2.7
Classifier: Programming Language :: Python :: 3.4
Classifier: Programming Language :: Python :: 3.5
Classifier: Programming Language :: Python :: 3.6
Classifier: Programming Language :: Python :: 3.7
Classifier: Programming Language :: Python :: 3.8
Classifier: Programming Language :: Python :: 3.9
Classifier: Programming Language :: Python :: 3.10
Classifier: Programming Language :: Python :: 3.11
Classifier: Programming Language :: Python :: 3.12
Classifier: Topic :: Software Development :: Libraries :: Python Modules
Classifier: Topic :: Text Processing :: Indexing
License-File: LICENSE.txt
Requires-Dist: cached-property
